YTLiveScrape/CommentsParser.py
YTLiveScrape/RequestJSONGenerator.py
YTLiveScrape/__init__.py
YTLiveScrape/live_chat_worker.py
YTLiveScrape-0.0.20.dist-info/LICENSE
YTLiveScrape-0.0.20.dist-info/METADATA
YTLiveScrape-0.0.20.dist-info/WHEEL
YTLiveScrape-0.0.20.dist-info/top_level.txt
YTLiveScrape-0.0.20.dist-info/RECORD
