Metadata-Version: 2.1
Name: YTLiveScrape
Version: 0.0.20
Summary: Simple YouTube Live scrape package
Home-page: https://github.com/BambooFlower/LiveYoutube-Scraper
License: UNKNOWN
Keywords: YouTube,Live comments,scrape
Platform: UNKNOWN
Classifier: Programming Language :: Python :: 3
Classifier: License :: OSI Approved :: MIT License
Classifier: Operating System :: OS Independent
Requires-Python: >=3.6
